pytest_minio_mock/__init__.py
pytest_minio_mock/plugin.py
pytest_minio_mock-0.4.19.dist-info/licenses/LICENSE
pytest_minio_mock-0.4.19.dist-info/METADATA
pytest_minio_mock-0.4.19.dist-info/WHEEL
pytest_minio_mock-0.4.19.dist-info/entry_points.txt
pytest_minio_mock-0.4.19.dist-info/top_level.txt
pytest_minio_mock-0.4.19.dist-info/RECORD
