Metadata-Version: 2.4
Name: pytest-minio-mock
Version: 0.4.19
Summary: A pytest plugin for mocking Minio S3 interactions
Author-email: Oussama Jarrousse <oussama@jarrousse.org>
License: MIT
Project-URL: Source, https://github.com/oussjarrousse/pytest-minio-mock/
Project-URL: Tracker, https://github.com/oussjarrousse/pytest-minio-mock/issues
Keywords: pytest,minio,mock
Classifier: Framework :: Pytest
Classifier: Programming Language :: Python :: 3
Classifier: License :: OSI Approved :: MIT License
Classifier: Operating System :: OS Independent
Classifier: Intended Audience :: Developers
Classifier: Programming Language :: Python :: 3.8
Classifier: Programming Language :: Python :: 3.9
Classifier: Programming Language :: Python :: 3.10
Classifier: Programming Language :: Python :: 3.11
Classifier: Programming Language :: Python :: 3.12
Classifier: Programming Language :: Python :: 3 :: Only
Classifier: Topic :: Software Development :: Testing
Requires-Python: >=3.8
License-File: LICENSE
Requires-Dist: pytest>=5.0.0
Requires-Dist: minio
Requires-Dist: pytest-mock
Requires-Dist: validators
Provides-Extra: dev
Requires-Dist: pre-commit; extra == "dev"
Requires-Dist: tox; extra == "dev"
Dynamic: license-file
